napari_swc_editor/__init__.py
napari_swc_editor/_reader.py
napari_swc_editor/_sample_data.py
napari_swc_editor/_version.py
napari_swc_editor/_widget.py
napari_swc_editor/_writer.py
napari_swc_editor/bindings.py
napari_swc_editor/napari.yaml
napari_swc_editor/swc_io.py
napari_swc_editor/_tests/__init__.py
napari_swc_editor/_tests/test_reader.py
napari_swc_editor/_tests/test_sample_data.py
napari_swc_editor/_tests/test_widget.py
napari_swc_editor/_tests/test_writer.py
napari_swc_editor-0.0.5.dist-info/LICENSE
napari_swc_editor-0.0.5.dist-info/METADATA
napari_swc_editor-0.0.5.dist-info/WHEEL
napari_swc_editor-0.0.5.dist-info/entry_points.txt
napari_swc_editor-0.0.5.dist-info/top_level.txt
napari_swc_editor-0.0.5.dist-info/RECORD
