Metadata-Version: 2.1
Name: napari-swc-editor
Version: 0.0.5
Summary: Use point and shape layer to edit swc format in napari
Author: Clément Caporal
Author-email: caporal.clement@gmail.com
License: 
Project-URL: Bug Tracker, https://github.com/LaboratoryOpticsBiosciences/napari-swc-editor/issues
Project-URL: Documentation, https://github.com/LaboratoryOpticsBiosciences/napari-swc-editor#README.md
Project-URL: Source Code, https://github.com/LaboratoryOpticsBiosciences/napari-swc-editor
Project-URL: User Support, https://github.com/LaboratoryOpticsBiosciences/napari-swc-editor/issues
Classifier: Development Status :: 2 - Pre-Alpha
Classifier: Framework :: napari
Classifier: Intended Audience :: Developers
Classifier: License :: OSI Approved :: BSD License
Classifier: Operating System :: OS Independent
Classifier: Programming Language :: Python
Classifier: Programming Language :: Python :: 3
Classifier: Programming Language :: Python :: 3 :: Only
Classifier: Programming Language :: Python :: 3.9
Classifier: Programming Language :: Python :: 3.10
Classifier: Programming Language :: Python :: 3.11
Classifier: Programming Language :: Python :: 3.12
Classifier: Topic :: Scientific/Engineering :: Image Processing
Requires-Python: >=3.9
License-File: LICENSE
Requires-Dist: numpy
Requires-Dist: magicgui
Requires-Dist: qtpy
Requires-Dist: scikit-image
Requires-Dist: pandas
Provides-Extra: testing
Requires-Dist: tox; extra == "testing"
Requires-Dist: pytest; extra == "testing"
Requires-Dist: pytest-cov; extra == "testing"
Requires-Dist: pytest-qt; extra == "testing"
Requires-Dist: napari; extra == "testing"
Requires-Dist: pyqt5; extra == "testing"
